faiss_searcher/__init__.py
faiss_searcher/base_encoder.py
faiss_searcher/bert_encoder.py
faiss_searcher/encoder_utils.py
faiss_searcher/faiss_searcher.py
faiss_searcher/vecs_whitening.py
faiss_searcher/backend/__init__.py
faiss_searcher/backend/base_encoder.py
faiss_searcher/backend/bert_encoder.py
faiss_searcher/backend/encoder_utils.py
faiss_searcher/backend/faiss_searcher.py
faiss_searcher/backend/vecs_whitening.py
faiss_searcher-0.1.10.dist-info/METADATA
faiss_searcher-0.1.10.dist-info/WHEEL
faiss_searcher-0.1.10.dist-info/top_level.txt
faiss_searcher-0.1.10.dist-info/RECORD
